gardenasmart/__init__.py
gardenasmart/client_api.py
gardenasmart-0.0.12.dist-info/DESCRIPTION.rst
gardenasmart-0.0.12.dist-info/LICENSE.txt
gardenasmart-0.0.12.dist-info/METADATA
gardenasmart-0.0.12.dist-info/RECORD
gardenasmart-0.0.12.dist-info/WHEEL
gardenasmart-0.0.12.dist-info/metadata.json
gardenasmart-0.0.12.dist-info/top_level.txt
