Metadata-Version: 2.0
Name: gardenasmart
Version: 0.0.12
Summary: Library to access the gardena smart platform
Home-page: UNKNOWN
Author: Peter Greberg
Author-email: peter@greberg.se
License: GPL
Platform: UNKNOWN
